promptground/__init__.py
promptground/promptground.py
promptground/models/PromptRunResult.py
promptground/models/__init__.py
promptground/utils/__init__.py
promptground/utils/utils.py
promptground/utils/validation.py
promptground-1.1.1.dist-info/LICENSE
promptground-1.1.1.dist-info/METADATA
promptground-1.1.1.dist-info/WHEEL
promptground-1.1.1.dist-info/top_level.txt
promptground-1.1.1.dist-info/RECORD
