Metadata-Version: 2.1
Name: promptground
Version: 1.1.1
Summary: A Python SDK for interacting with PromptGround API.
Home-page: https://promptground.io
Author: NoCode, Inc.
Classifier: Programming Language :: Python :: 3
Classifier: License :: OSI Approved :: MIT License
Classifier: Operating System :: OS Independent
Requires-Python: >=3.6
License-File: LICENSE
Requires-Dist: requests>=2.25.1
